airflow_common/__init__.py
airflow_common/airflow/__init__.py
airflow_common/airflow/operators.py
airflow_common/airflow/topology.py
airflow_common/infra/__init__.py
airflow_common/infra/commands.py
airflow_common/infra/task.py
airflow_common/library/__init__.py
airflow_common/library/model.py
airflow_common/library/task.py
airflow_common/tests/conftest.py
airflow_common/tests/test_git.py
airflow_common/tests/test_helpers.py
airflow_common/tests/test_journalctl.py
airflow_common/tests/test_library.py
airflow_common/tests/config/config.yaml
airflow_common/tests/config/extensions/libraries.yaml
airflow_common-0.7.8.dist-info/METADATA
airflow_common-0.7.8.dist-info/WHEEL
airflow_common-0.7.8.dist-info/licenses/LICENSE
airflow_common-0.7.8.dist-info/RECORD
